{"nodes": [{"id": "c_mamp_htdocs_the_base_src_pages_contact_tsx", "label": "Contact.tsx", "file_type": "code", "source_file": "C:\\MAMP\\htdocs\\The-Base\\src\\pages\\Contact.tsx", "source_location": "L1"}, {"id": "pages_contact_contact", "label": "Contact()", "file_type": "code", "source_file": "C:\\MAMP\\htdocs\\The-Base\\src\\pages\\Contact.tsx", "source_location": "L9"}], "edges": [{"source": "c_mamp_htdocs_the_base_src_pages_contact_tsx", "target": "react", "relation": "imports_from", "context": "import", "confidence": "EXTRACTED", "source_file": "C:\\MAMP\\htdocs\\The-Base\\src\\pages\\Contact.tsx", "source_location": "L1", "weight": 1.0}, {"source": "c_mamp_htdocs_the_base_src_pages_contact_tsx", "target": "lucide_react", "relation": "imports_from", "context": "import", "confidence": "EXTRACTED", "source_file": "C:\\MAMP\\htdocs\\The-Base\\src\\pages\\Contact.tsx", "source_location": "L2", "weight": 1.0}, {"source": "c_mamp_htdocs_the_base_src_pages_contact_tsx", "target": "c_mamp_htdocs_the_base_src_components_ui_brandline_tsx", "relation": "imports_from", "context": "import", "confidence": "EXTRACTED", "source_file": "C:\\MAMP\\htdocs\\The-Base\\src\\pages\\Contact.tsx", "source_location": "L3", "weight": 1.0}, {"source": "c_mamp_htdocs_the_base_src_pages_contact_tsx", "target": "ui_brandline_brandline", "relation": "imports", "context": "import", "confidence": "EXTRACTED", "source_file": "C:\\MAMP\\htdocs\\The-Base\\src\\pages\\Contact.tsx", "source_location": "L3", "weight": 1.0}, {"source": "c_mamp_htdocs_the_base_src_pages_contact_tsx", "target": "c_mamp_htdocs_the_base_src_components_ui_neon_button_tsx", "relation": "imports_from", "context": "import", "confidence": "EXTRACTED", "source_file": "C:\\MAMP\\htdocs\\The-Base\\src\\pages\\Contact.tsx", "source_location": "L4", "weight": 1.0}, {"source": "c_mamp_htdocs_the_base_src_pages_contact_tsx", "target": "ui_neon_button_button", "relation": "imports", "context": "import", "confidence": "EXTRACTED", "source_file": "C:\\MAMP\\htdocs\\The-Base\\src\\pages\\Contact.tsx", "source_location": "L4", "weight": 1.0}, {"source": "c_mamp_htdocs_the_base_src_pages_contact_tsx", "target": "c_mamp_htdocs_the_base_src_services_adminservice_ts", "relation": "imports_from", "context": "import", "confidence": "EXTRACTED", "source_file": "C:\\MAMP\\htdocs\\The-Base\\src\\pages\\Contact.tsx", "source_location": "L5", "weight": 1.0}, {"source": "c_mamp_htdocs_the_base_src_pages_contact_tsx", "target": "services_adminservice_adminservice", "relation": "imports", "context": "import", "confidence": "EXTRACTED", "source_file": "C:\\MAMP\\htdocs\\The-Base\\src\\pages\\Contact.tsx", "source_location": "L5", "weight": 1.0}, {"source": "c_mamp_htdocs_the_base_src_pages_contact_tsx", "target": "c_mamp_htdocs_the_base_src_hooks_usebranding_ts", "relation": "imports_from", "context": "import", "confidence": "EXTRACTED", "source_file": "C:\\MAMP\\htdocs\\The-Base\\src\\pages\\Contact.tsx", "source_location": "L6", "weight": 1.0}, {"source": "c_mamp_htdocs_the_base_src_pages_contact_tsx", "target": "hooks_usebranding_usebranding", "relation": "imports", "context": "import", "confidence": "EXTRACTED", "source_file": "C:\\MAMP\\htdocs\\The-Base\\src\\pages\\Contact.tsx", "source_location": "L6", "weight": 1.0}, {"source": "c_mamp_htdocs_the_base_src_pages_contact_tsx", "target": "c_mamp_htdocs_the_base_src_components_seo_tsx", "relation": "imports_from", "context": "import", "confidence": "EXTRACTED", "source_file": "C:\\MAMP\\htdocs\\The-Base\\src\\pages\\Contact.tsx", "source_location": "L7", "weight": 1.0}, {"source": "c_mamp_htdocs_the_base_src_pages_contact_tsx", "target": "pages_contact_contact", "relation": "contains", "confidence": "EXTRACTED", "source_file": "C:\\MAMP\\htdocs\\The-Base\\src\\pages\\Contact.tsx", "source_location": "L9", "weight": 1.0}], "raw_calls": [{"caller_nid": "pages_contact_contact", "callee": "useBranding", "is_member_call": false, "source_file": "C:\\MAMP\\htdocs\\The-Base\\src\\pages\\Contact.tsx", "source_location": "L10"}, {"caller_nid": "pages_contact_contact", "callee": "useState", "is_member_call": false, "source_file": "C:\\MAMP\\htdocs\\The-Base\\src\\pages\\Contact.tsx", "source_location": "L11"}, {"caller_nid": "pages_contact_contact", "callee": "useState", "is_member_call": false, "source_file": "C:\\MAMP\\htdocs\\The-Base\\src\\pages\\Contact.tsx", "source_location": "L12"}]}